mjinx/__init__.py
mjinx/problem.py
mjinx/typing.py
mjinx/visualize.py
mjinx/components/__init__.py
mjinx/components/_base.py
mjinx/components/barriers/__init__.py
mjinx/components/barriers/_base.py
mjinx/components/barriers/_joint_barrier.py
mjinx/components/barriers/_obj_barrier.py
mjinx/components/barriers/_obj_position_barrier.py
mjinx/components/barriers/_self_collision_barrier.py
mjinx/components/tasks/__init__.py
mjinx/components/tasks/_base.py
mjinx/components/tasks/_com_task.py
mjinx/components/tasks/_joint_task.py
mjinx/components/tasks/_obj_frame_task.py
mjinx/components/tasks/_obj_position_task.py
mjinx/components/tasks/_obj_task.py
mjinx/configuration/__init__.py
mjinx/configuration/_collision.py
mjinx/configuration/_lie.py
mjinx/configuration/_model.py
mjinx/solvers/__init__.py
mjinx/solvers/_base.py
mjinx/solvers/_global_ik.py
mjinx/solvers/_local_ik.py
mjinx-1.0.0.dist-info/LICENSE
mjinx-1.0.0.dist-info/METADATA
mjinx-1.0.0.dist-info/WHEEL
mjinx-1.0.0.dist-info/top_level.txt
mjinx-1.0.0.dist-info/RECORD
