Metadata-Version: 2.1
Name: mjinx
Version: 1.0.0
Summary: Numerical Inverse Kinematics based on JAX + MJX
Author-email: Ivan Domrachev <domrachev10@gmail.com>, Simeon Nedelchev <simkaned@gmail.com>, Lev Kozlov <kozlov.l.a10@gmail.com>
Requires-Python: >=3.10
License-File: LICENSE
Requires-Dist: mujoco
Requires-Dist: mujoco-mjx
Requires-Dist: jaxlib>=0.4
Requires-Dist: jaxopt
Requires-Dist: jax>=0.4
Requires-Dist: jaxlie>=1.4
Requires-Dist: jax-dataclasses>=1.6.0
Requires-Dist: optax>=0.2
Provides-Extra: all
Requires-Dist: mjinx[dev,docs,visual]; extra == "all"
Provides-Extra: dev
Requires-Dist: robot-descriptions>=1.12; extra == "dev"
Requires-Dist: pre-commit; extra == "dev"
Requires-Dist: ruff; extra == "dev"
Requires-Dist: pytest; extra == "dev"
Provides-Extra: docs
Requires-Dist: sphinx>=8; extra == "docs"
Requires-Dist: sphinx-mathjax-offline; extra == "docs"
Requires-Dist: sphinx-autodoc-typehints; extra == "docs"
Requires-Dist: sphinx-rtd-theme>1; extra == "docs"
Provides-Extra: visual
Requires-Dist: dm-control; extra == "visual"
Requires-Dist: mediapy; extra == "visual"
